Graphs/DirectedGraph.py
Graphs/Graph.py
Graphs/UndirectedGraph.py
Graphs/__init__.py
Graphs/Contracts/IGraph.py
Graphs/Contracts/__init__.py
Lists/ArrayList.py
Lists/LinkedList.py
Lists/__init__.py
Lists/Contracts/IList.py
Lists/Contracts/Iterateable.py
Lists/Contracts/Searchable.py
Lists/Contracts/Sortable.py
Lists/Contracts/__init__.py
Trees/BinarySearchTree.py
Trees/__init__.py
Trees/Contracts/ITree.py
Trees/Contracts/__init__.py
hsbmaulana_pycollection-1.0.0.dist-info/LICENSE
hsbmaulana_pycollection-1.0.0.dist-info/METADATA
hsbmaulana_pycollection-1.0.0.dist-info/WHEEL
hsbmaulana_pycollection-1.0.0.dist-info/top_level.txt
hsbmaulana_pycollection-1.0.0.dist-info/RECORD
