Metadata-Version: 2.1
Name: hsbmaulana-pycollection
Version: 1.0.0
Summary: Data Structure and Algorithm
Author-email: Hasby Maulana <hsbmaulana.iso@protonmail.com>
License: MIT License
Project-URL: homepage, https://github.com/hsbmaulana/pycollection
Project-URL: bug, https://github.com/hsbmaulana/pycollection/issues
Classifier: Programming Language :: Python :: 3.9
Classifier: Topic :: Software Development :: Libraries :: Python Modules
Requires-Python: >=3.9.6
License-File: LICENSE
Provides-Extra: test
Requires-Dist: pytest (>=7.2.0) ; extra == 'test'
